core/module/comparator4_cascade.sv
module comparator4_cascade (
    input logic [3:0] a,
    input logic [3:0] b,

    input logic i_eq,
    input logic i_lt,
    input logic i_gt,

    output logic o_eq,
    output logic o_lt,
    output logic o_gt
);
    logic local_eq3, local_eq2, local_eq1, local_eq0;
    assign local_eq3 = ~(a[3] ^ b[3]);
    assign local_eq2 = ~(a[2] ^ b[2]);
    assign local_eq1 = ~(a[1] ^ b[1]);
    assign local_eq0 = ~(a[0] ^ b[0]);

    assign local_eq = local_eq3 & local_eq2 & local_eq1 & local_eq0;
    assign local_gt = (a[3] & ~b[3]) | (local_eq3 & a[2] & ~b[2]) | (local_eq3 & local_eq2 & a[1] & ~b[1]) | (local_eq3 & local_eq2 & local_eq1 & a[0] & ~b[0]);
    assign local_lt = ~(local_gt | local_eq);

    assign o_eq = (local_eq & i_eq);
    assign o_gt = (local_gt | (local_eq & i_gt));
    assign o_lt = (local_lt | (local_eq & i_lt));

endmodule

core/module/comparator32.sv
module comparator32 (
    input logic [31:0] i_a,
    input logic [31:0] i_b,

    output logic o_eq,
    output logic o_lt,
    output logic o_gt
);
    logic [6:0] c_eq, c_lt, c_gt;

    comparator4_cascade cmp0 (
        .a (i_a[3:0]),
        .b (i_b[3:0]),
        .i_eq (1'b1),
        .i_lt (1'b0),
        .i_gt (1'b0),
        .o_eq (c_eq[0]),
        .o_lt (c_lt[0]),
        .o_gt (c_gt[0])
    );

    comparator4_cascade cmp1 (
        .a (i_a[7:4]),
        .b (i_b[7:4]),
        .i_eq (c_eq[0]),
        .i_lt (c_lt[0]),
        .i_gt (c_gt[0]),
        .o_eq (c_eq[1]),
        .o_lt (c_lt[1]),
        .o_gt (c_gt[1])
    );

    comparator4_cascade cmp2 (
        .a (i_a[11:8]),
        .b (i_b[11:8]),
        .i_eq (c_eq[1]),
        .i_lt (c_lt[1]),
        .i_gt (c_gt[1]),
        .o_eq (c_eq[2]),
        .o_lt (c_lt[2]),
        .o_gt (c_gt[2])
    );

    comparator4_cascade cmp3 (
        .a (i_a[15:12]),
        .b (i_b[15:12]),
        .i_eq (c_eq[2]),
        .i_lt (c_lt[2]),
        .i_gt (c_gt[2]),
        .o_eq (c_eq[3]),
        .o_lt (c_lt[3]),
        .o_gt (c_gt[3])
    );

    comparator4_cascade cmp4 (
        .a (i_a[19:16]),
        .b (i_b[19:16]),
        .i_eq (c_eq[3]),
        .i_lt (c_lt[3]),
        .i_gt (c_gt[3]),
        .o_eq (c_eq[4]),
        .o_lt (c_lt[4]),
        .o_gt (c_gt[4])
    );

    comparator4_cascade cmp5 (
        .a (i_a[23:20]),
        .b (i_b[23:20]),
        .i_eq (c_eq[4]),
        .i_lt (c_lt[4]),
        .i_gt (c_gt[4]),
        .o_eq (c_eq[5]),
        .o_lt (c_lt[5]),
        .o_gt (c_gt[5])
    );

    comparator4_cascade cmp6 (
        .a (i_a[27:24]),
        .b (i_b[27:24]),
        .i_eq (c_eq[5]),
        .i_lt (c_lt[5]),
        .i_gt (c_gt[5]),
        .o_eq (c_eq[6]),
        .o_lt (c_lt[6]),
        .o_gt (c_gt[6])
    );

    comparator4_cascade cmp7 (
        .a (i_a[31:28]),
        .b (i_b[31:28]),
        .i_eq (c_eq[6]),
        .i_lt (c_lt[6]),
        .i_gt (c_gt[6]),
        .o_eq (o_eq),
        .o_lt (o_lt),
        .o_gt (o_gt)
    );

endmodule

core/module/brc.sv
module brc (
    input logic [31:0] i_rs1_data,
    input logic [31:0] i_rs2_data,
    input logic i_br_un,

    output logic o_br_less,
    output logic o_br_equal
);

    logic unsigned_gt, unsigned_eq, unsigned_lt;
    logic signed_eq, signed_lt;

    comparator32 u_comparator32 (
        .i_a (i_rs1_data),
        .i_b (i_rs2_data),
        .o_lt (unsigned_lt),
        .o_eq (unsigned_eq),
        .o_gt (unsigned_gt)
    );

    assign sign_eq = ~(i_rs1_data[31] ^ i_rs2_data[31]);
    assign signed_lt = (i_rs1_data[31] & ~i_rs2_data[31]) | (sign_eq & unsigned_lt);

    assign o_br_less = i_br_un ? signed_lt : unsigned_lt;
    assign o_br_equal = unsigned_eq;

endmodule

testbench/module/brc_tb.sv
`timescale 1ns/1ps

module brc_tb;

    // =========================================================
    // DUT signals
    // =========================================================

    logic [31:0] i_rs1_data;
    logic [31:0] i_rs2_data;
    logic        i_br_un;

    logic        o_br_less;
    logic        o_br_equal;


    // =========================================================
    // Instantiate DUT
    // =========================================================

    brc dut (
        .i_rs1_data (i_rs1_data),
        .i_rs2_data (i_rs2_data),
        .i_br_un    (i_br_un),
        .o_br_less  (o_br_less),
        .o_br_equal (o_br_equal)
    );


    // =========================================================
    // Reference model
    //
    // Built-in comparison operators are used ONLY
    // for verification.
    // =========================================================

    function automatic logic expected_less (
        input logic [31:0] a,
        input logic [31:0] b,
        input logic        br_un
    );

        logic signed [31:0] signed_a;
        logic signed [31:0] signed_b;

        begin

            signed_a = a;
            signed_b = b;

            if (br_un)
                expected_less = (signed_a < signed_b);
            else
                expected_less = (a < b);

        end

    endfunction


    function automatic logic expected_equal (
        input logic [31:0] a,
        input logic [31:0] b
    );

        begin
            expected_equal = (a == b);
        end

    endfunction


    // =========================================================
    // Check one testcase
    // =========================================================

    task automatic check_case (
        input logic [31:0] a,
        input logic [31:0] b,
        input logic        br_un
    );

        logic expected_less_value;
        logic expected_equal_value;

        begin

            i_rs1_data = a;
            i_rs2_data = b;
            i_br_un    = br_un;

            #1;

            expected_less_value =
                expected_less(a, b, br_un);

            expected_equal_value =
                expected_equal(a, b);


            assert (o_br_less === expected_less_value)
            else begin
                $error("LESS FAIL: rs1=%h rs2=%h br_un=%b expected=%b actual=%b",
                    a, b, br_un,
                    expected_less_value, o_br_less);
            end

            assert (o_br_equal === expected_equal_value)
            else begin
                $error("EQUAL FAIL: rs1=%h rs2=%h expected=%b actual=%b",
                    a, b,
                    expected_equal_value, o_br_equal);
            end

        end

    endtask


    // =========================================================
    // Test
    // =========================================================

    initial begin

        $dumpfile("sim/module/brc_tb.vcd");
        $dumpvars(0, brc_tb);

        $display("==========================================");
        $display("            BRC TESTBENCH");
        $display("==========================================");


        // =====================================================
        // 1. UNSIGNED TEST
        // =====================================================

        $display("\n[1] UNSIGNED TEST");


        // 5 < 10
        check_case(
            32'd5,
            32'd10,
            1'b0
        );


        // 10 < 5 -> false
        check_case(
            32'd10,
            32'd5,
            1'b0
        );


        // 5 = 5
        check_case(
            32'd5,
            32'd5,
            1'b0
        );


        // 0 < FFFFFFFF
        check_case(
            32'h00000000,
            32'hFFFFFFFF,
            1'b0
        );


        // FFFFFFFF < 0 -> false
        check_case(
            32'hFFFFFFFF,
            32'h00000000,
            1'b0
        );


        // =====================================================
        // 2. SIGNED TEST
        // =====================================================

        $display("\n[2] SIGNED TEST");


        // +5 < +10
        check_case(
            32'd5,
            32'd10,
            1'b1
        );


        // +10 < +5 -> false
        check_case(
            32'd10,
            32'd5,
            1'b1
        );


        // -1 < +1
        check_case(
            32'hFFFFFFFF,
            32'h00000001,
            1'b1
        );


        // +1 < -1 -> false
        check_case(
            32'h00000001,
            32'hFFFFFFFF,
            1'b1
        );


        // -10 < -5
        check_case(
            32'hFFFFFFF6,
            32'hFFFFFFFB,
            1'b1
        );


        // -5 < -10 -> false
        check_case(
            32'hFFFFFFFB,
            32'hFFFFFFF6,
            1'b1
        );


        // -1 = -1
        check_case(
            32'hFFFFFFFF,
            32'hFFFFFFFF,
            1'b1
        );


        // 0 = 0
        check_case(
            32'h00000000,
            32'h00000000,
            1'b1
        );


        // =====================================================
        // 3. IMPORTANT SIGN DIFFERENCE TEST
        // =====================================================

        $display("\n[3] SIGN DIFFERENCE TEST");


        // Same numbers, unsigned vs signed
        //
        // FFFFFFFF:
        //   unsigned = 4294967295
        //   signed   = -1
        //
        // Compare with 1.

        // Unsigned: FFFFFFFF < 1 = false
        check_case(
            32'hFFFFFFFF,
            32'h00000001,
            1'b0
        );

        // Signed: -1 < 1 = true
        check_case(
            32'hFFFFFFFF,
            32'h00000001,
            1'b1
        );


        // =====================================================
        // 4. BOUNDARY VALUES
        // =====================================================

        $display("\n[4] BOUNDARY VALUES");


        // Signed INT_MIN < 0
        check_case(
            32'h80000000,
            32'h00000000,
            1'b1
        );


        // 0 < INT_MAX
        check_case(
            32'h00000000,
            32'h7FFFFFFF,
            1'b1
        );


        // INT_MAX < INT_MIN -> false
        check_case(
            32'h7FFFFFFF,
            32'h80000000,
            1'b1
        );


        // Unsigned 0 < INT_MIN representation
        check_case(
            32'h00000000,
            32'h80000000,
            1'b0
        );


        // Unsigned INT_MIN representation < 0 -> false
        check_case(
            32'h80000000,
            32'h00000000,
            1'b0
        );


        // =====================================================
        // 5. RANDOMIZED TEST
        // =====================================================

        $display("\n[5] RANDOMIZED TEST");

        repeat (1000) begin

            check_case(
                $urandom,
                $urandom,
                1'b0
            );

            check_case(
                $urandom,
                $urandom,
                1'b1
            );

        end


        // =====================================================
        // Finish
        // =====================================================

        $display("\n==========================================");
        $display("         BRC TEST COMPLETED");
        $display("==========================================");

        $finish;

    end

endmodule

sim/module/brc_tb.vcd
$date
	Fri Oct  2 01:50:43 2026
$end
$version
	Icarus Verilog
$end
$timescale
	1ps
$end
$scope module brc_tb $end
$var wire 1 ! o_br_less $end
$var wire 1 " o_br_equal $end
$var reg 1 # i_br_un $end
$var reg 32 $ i_rs1_data [31:0] $end
$var reg 32 % i_rs2_data [31:0] $end
$scope function expected_equal $end
$upscope $end
$scope function expected_less $end
$upscope $end
$scope module dut $end
$var wire 1 # i_br_un $end
$var wire 32 & i_rs1_data [31:0] $end
$var wire 32 ' i_rs2_data [31:0] $end
$var wire 1 " o_br_equal $end
$var wire 1 ( sign_eq $end
$var wire 1 ) signed_lt $end
$var wire 1 * unsigned_lt $end
$var wire 1 + unsigned_gt $end
$var wire 1 , unsigned_eq $end
$var wire 1 ! o_br_less $end
$scope module u_comparator32 $end
$var wire 32 - i_a [31:0] $end
$var wire 32 . i_b [31:0] $end
$var wire 1 * o_lt $end
$var wire 1 + o_gt $end
$var wire 1 , o_eq $end
$var wire 7 / c_lt [6:0] $end
$var wire 7 0 c_gt [6:0] $end
$var wire 7 1 c_eq [6:0] $end
$scope module cmp0 $end
$var wire 4 2 a [3:0] $end
$var wire 4 3 b [3:0] $end
$var wire 1 4 i_eq $end
$var wire 1 5 i_gt $end
$var wire 1 6 i_lt $end
$var wire 1 7 local_eq $end
$var wire 1 8 local_eq0 $end
$var wire 1 9 local_eq1 $end
$var wire 1 : local_eq2 $end
$var wire 1 ; local_eq3 $end
$var wire 1 < local_gt $end
$var wire 1 = local_lt $end
$var wire 1 > o_eq $end
$var wire 1 ? o_gt $end
$var wire 1 @ o_lt $end
$upscope $end
$scope module cmp1 $end
$var wire 4 A a [3:0] $end
$var wire 4 B b [3:0] $end
$var wire 1 C i_eq $end
$var wire 1 D i_gt $end
$var wire 1 E i_lt $end
$var wire 1 F local_eq $end
$var wire 1 G local_eq0 $end
$var wire 1 H local_eq1 $end
$var wire 1 I local_eq2 $end
$var wire 1 J local_eq3 $end
$var wire 1 K local_gt $end
$var wire 1 L local_lt $end
$var wire 1 M o_eq $end
$var wire 1 N o_gt $end
$var wire 1 O o_lt $end
$upscope $end
$scope module cmp2 $end
$var wire 4 P a [3:0] $end
$var wire 4 Q b [3:0] $end
$var wire 1 R i_eq $end
$var wire 1 S i_gt $end
$var wire 1 T i_lt $end
$var wire 1 U local_eq $end
$var wire 1 V local_eq0 $end
$var wire 1 W local_eq1 $end
$var wire 1 X local_eq2 $end
$var wire 1 Y local_eq3 $end
$var wire 1 Z local_gt $end
$var wire 1 [ local_lt $end
$var wire 1 \ o_eq $end
$var wire 1 ] o_gt $end
$var wire 1 ^ o_lt $end
$upscope $end
$scope module cmp3 $end
$var wire 4 _ a [3:0] $end
$var wire 4 ` b [3:0] $end
$var wire 1 a i_eq $end
$var wire 1 b i_gt $end
$var wire 1 c i_lt $end
$var wire 1 d local_eq $end
$var wire 1 e local_eq0 $end
$var wire 1 f local_eq1 $end
$var wire 1 g local_eq2 $end
$var wire 1 h local_eq3 $end
$var wire 1 i local_gt $end
$var wire 1 j local_lt $end
$var wire 1 k o_eq $end
$var wire 1 l o_gt $end
$var wire 1 m o_lt $end
$upscope $end
$scope module cmp4 $end
$var wire 4 n a [3:0] $end
$var wire 4 o b [3:0] $end
$var wire 1 p i_eq $end
$var wire 1 q i_gt $end
$var wire 1 r i_lt $end
$var wire 1 s local_eq $end
$var wire 1 t local_eq0 $end
$var wire 1 u local_eq1 $end
$var wire 1 v local_eq2 $end
$var wire 1 w local_eq3 $end
$var wire 1 x local_gt $end
$var wire 1 y local_lt $end
$var wire 1 z o_eq $end
$var wire 1 { o_gt $end
$var wire 1 | o_lt $end
$upscope $end
$scope module cmp5 $end
$var wire 4 } a [3:0] $end
$var wire 4 ~ b [3:0] $end
$var wire 1 !" i_eq $end
$var wire 1 "" i_gt $end
$var wire 1 #" i_lt $end
$var wire 1 $" local_eq $end
$var wire 1 %" local_eq0 $end
$var wire 1 &" local_eq1 $end
$var wire 1 '" local_eq2 $end
$var wire 1 (" local_eq3 $end
$var wire 1 )" local_gt $end
$var wire 1 *" local_lt $end
$var wire 1 +" o_eq $end
$var wire 1 ," o_gt $end
$var wire 1 -" o_lt $end
$upscope $end
$scope module cmp6 $end
$var wire 4 ." a [3:0] $end
$var wire 4 /" b [3:0] $end
$var wire 1 0" i_eq $end
$var wire 1 1" i_gt $end
$var wire 1 2" i_lt $end
$var wire 1 3" local_eq $end
$var wire 1 4" local_eq0 $end
$var wire 1 5" local_eq1 $end
$var wire 1 6" local_eq2 $end
$var wire 1 7" local_eq3 $end
$var wire 1 8" local_gt $end
$var wire 1 9" local_lt $end
$var wire 1 :" o_eq $end
$var wire 1 ;" o_gt $end
$var wire 1 <" o_lt $end
$upscope $end
$scope module cmp7 $end
$var wire 4 =" a [3:0] $end
$var wire 4 >" b [3:0] $end
$var wire 1 ?" i_eq $end
$var wire 1 @" i_gt $end
$var wire 1 A" i_lt $end
$var wire 1 B" local_eq $end
$var wire 1 C" local_eq0 $end
$var wire 1 D" local_eq1 $end
$var wire 1 E" local_eq2 $end
$var wire 1 F" local_eq3 $end
$var wire 1 G" local_gt $end
$var wire 1 H" local_lt $end
$var wire 1 , o_eq $end
$var wire 1 + o_gt $end
$var wire 1 * o_lt $end
$upscope $end
$upscope $end
$upscope $end
$scope task check_case $end
$upscope $end
$upscope $end
$enddefinitions $end
$comment Show the parameter values. $end
$dumpall
$end
#0
$dumpvars
0H"
0G"
1F"
1E"
1D"
1C"
1B"
1A"
0@"
0?"
b0 >"
b0 ="
1<"
0;"
0:"
09"
08"
17"
16"
15"
14"
13"
12"
01"
00"
b0 /"
b0 ."
1-"
0,"
0+"
0*"
0)"
1("
1'"
1&"
1%"
1$"
1#"
0""
0!"
b0 ~
b0 }
1|
0{
0z
0y
0x
1w
1v
1u
1t
1s
1r
0q
0p
b0 o
b0 n
1m
0l
0k
0j
0i
1h
1g
1f
1e
1d
1c
0b
0a
b0 `
b0 _
1^
0]
0\
0[
0Z
1Y
1X
1W
1V
1U
1T
0S
0R
b0 Q
b0 P
1O
0N
0M
0L
0K
1J
1I
1H
1G
1F
1E
0D
0C
b0 B
b0 A
1@
0?
0>
1=
0<
0;
0:
09
08
07
06
05
14
b1010 3
b101 2
b0 1
b0 0
b1111111 /
b1010 .
b101 -
0,
0+
1*
1)
1(
b1010 '
b101 &
b1010 %
b101 $
0#
0"
1!
$end
#1000
0)
0!
0*
0A"
1+
0<"
1@"
02"
1;"
0-"
11"
0#"
1,"
0|
1""
0r
1{
0m
1q
0c
1l
0^
1b
0T
1]
0O
1S
0E
1N
b0 /
0@
0=
1D
b1111111 0
1?
1<
b101 3
b1010 2
b101 %
b101 '
b101 .
b1010 $
b1010 &
b1010 -
#2000
0)
0!
0*
0A"
0+
0<"
0@"
02"
0;"
0-"
01"
1"
1,
0#"
0,"
1?"
0|
1:"
0""
10"
0r
0{
1+"
0m
1!"
0q
1z
0c
0l
1p
0^
1k
0b
1a
0T
0]
1\
0O
1R
0S
1M
0E
0N
1C
b0 /
0@
b1111111 1
1>
0=
0D
17
b0 0
0?
0<
1;
1:
19
18
b101 2
b101 $
b101 &
b101 -
#3000
1T
1c
1r
1#"
12"
1A"
1!
1E
1O
1^
1m
1|
1-"
1<"
1*
b1111111 /
1@
1L
0R
1[
0a
1j
0p
1y
0!"
1*"
00"
19"
0?"
1H"
1=
0C
0M
0\
0k
0z
0+"
0:"
0"
0,
b0 1
0>
0F
0U
0d
0s
0$"
03"
0B"
07
0;
09
0J
0I
0H
0G
0Y
0X
0W
0V
0h
0g
0f
0e
0w
0v
0u
0t
0("
0'"
0&"
0%"
07"
06"
05"
04"
0F"
0E"
0D"
0C"
0:
08
0(
b1111 3
b1111 B
b1111 Q
b1111 `
b1111 o
b1111 ~
b1111 /"
b1111 >"
b0 2
b11111111111111111111111111111111 %
b11111111111111111111111111111111 '
b11111111111111111111111111111111 .
b0 $
b0 &
b0 -
#4000
0E
0T
0c
0r
0#"
02"
0A"
0!
0@
0O
0^
0m
0|
0-"
b0 /
0<"
0*
0=
1D
0L
1S
0[
1b
0j
1q
0y
1""
0*"
11"
09"
1@"
0H"
1?
1N
1]
1l
1{
1,"
b1111111 0
1;"
1+
1<
1K
1Z
1i
1x
1)"
18"
1G"
1)
b0 3
b0 B
b0 Q
b0 `
b0 o
b0 ~
b0 /"
b0 >"
b1111 2
b1111 A
b1111 P
b1111 _
b1111 n
b1111 }
b1111 ."
b1111 ="
b0 %
b0 '
b0 .
b11111111111111111111111111111111 $
b11111111111111111111111111111111 &
b11111111111111111111111111111111 -
#5000
1E
1T
1c
1r
1#"
12"
1A"
1@
1O
1^
1m
1|
1-"
b1111111 /
1<"
1*
1=
0D
0L
0S
0[
0b
0j
0q
0y
0""
0*"
01"
09"
0@"
0H"
0?
1F
0N
1U
0]
1d
0l
1s
0{
1$"
0,"
13"
b0 0
0;"
1B"
0+
0<
0K
0Z
0i
0x
0)"
08"
0G"
1J
1I
1H
1G
1Y
1X
1W
1V
1h
1g
1f
1e
1w
1v
1u
1t
1("
1'"
1&"
1%"
17"
16"
15"
14"
1F"
1E"
1D"
1C"
1(
1)
1!
b1010 3
b101 2
b0 A
b0 P
b0 _
b0 n
b0 }
b0 ."
b0 ="
1#
b1010 %
b1010 '
b1010 .
b101 $
b101 &
b101 -
#6000
0!
0)
0*
0A"
1+
0<"
1@"
02"
1;"
0-"
11"
0#"
1,"
0|
1""
0r
1{
0m
1q
0c
1l
0^
1b
0T
1]
0O
1S
0E
1N
b0 /
0@
0=
1D
b1111111 0
1?
1<
b101 3
b1010 2
b101 %
b101 '
b101 .
b1010 $
b1010 &
b1010 -
#7000
0F
1K
0U
1Z
0d
1i
0s
1x
0$"
1)"
03"
18"
0B"
1G"
1!
18
0J
0I
0H
0G
0Y
0X
0W
0V
0h
0g
0f
0e
0w
0v
0u
0t
0("
0'"
0&"
0%"
07"
06"
05"
04"
0F"
0E"
0D"
0C"
0(
1)
b1 3
b1111 2
b1111 A
b1111 P
b1111 _
b1111 n
b1111 }
b1111 ."
b1111 ="
b1 %
b1 '
b1 .
b11111111111111111111111111111111 $
b11111111111111111111111111111111 &
b11111111111111111111111111111111 -
#8000
1E
1T
1c
1r
1#"
12"
1A"
1@
1O
1^
1m
1|
1-"
b1111111 /
1<"
1*
1=
0D
1L
0S
1[
0b
1j
0q
1y
0""
1*"
01"
19"
0@"
1H"
0?
0N
0]
0l
0{
0,"
b0 0
0;"
0+
0<
0K
0Z
0i
0x
0)"
08"
0G"
0!
0)
b1111 3
b1111 B
b1111 Q
b1111 `
b1111 o
b1111 ~
b1111 /"
b1111 >"
b1 2
b0 A
b0 P
b0 _
b0 n
b0 }
b0 ."
b0 ="
b11111111111111111111111111111111 %
b11111111111111111111111111111111 '
b11111111111111111111111111111111 .
b1 $
b1 &
b1 -
#9000
0L
0[
0j
0y
0*"
09"
0H"
1F
1U
1d
1s
1$"
13"
1B"
1!
1)
19
08
1J
1I
1H
1G
1Y
1X
1W
1V
1h
1g
1f
1e
1w
1v
1u
1t
1("
1'"
1&"
1%"
17"
16"
15"
14"
1F"
1E"
1D"
1C"
1(
b1011 3
b110 2
b1111 A
b1111 P
b1111 _
b1111 n
b1111 }
b1111 ."
b1111 ="
b11111111111111111111111111111011 %
b11111111111111111111111111111011 '
b11111111111111111111111111111011 .
b11111111111111111111111111110110 $
b11111111111111111111111111110110 &
b11111111111111111111111111110110 -
#10000
0!
0)
0*
0A"
1+
0<"
1@"
02"
1;"
0-"
11"
0#"
1,"
0|
1""
0r
1{
0m
1q
0c
1l
0^
1b
0T
1]
0O
1S
0E
1N
b0 /
0@
0=
1D
b1111111 0
1?
1<
b110 3
b1011 2
b11111111111111111111111111110110 %
b11111111111111111111111111110110 '
b11111111111111111111111111110110 .
b11111111111111111111111111111011 $
b11111111111111111111111111111011 &
b11111111111111111111111111111011 -
#11000
0+
0@"
0;"
01"
0,"
1"
1,
0""
1?"
0{
1:"
10"
0q
1+"
0l
1!"
1z
0b
1p
0]
1k
1a
0S
1\
0N
1R
1M
0D
1C
b0 0
0?
b1111111 1
1>
0<
17
1;
18
1:
b1111 3
b1111 2
b11111111111111111111111111111111 %
b11111111111111111111111111111111 '
b11111111111111111111111111111111 .
b11111111111111111111111111111111 $
b11111111111111111111111111111111 &
b11111111111111111111111111111111 -
#12000
b0 3
b0 B
b0 Q
b0 `
b0 o
b0 ~
b0 /"
b0 >"
b0 2
b0 A
b0 P
b0 _
b0 n
b0 }
b0 ."
b0 ="
b0 %
b0 '
b0 .
b0 $
b0 &
b0 -
#13000
0C
1D
0>
1?
0R
1S
0a
1b
0p
1q
0!"
1""
00"
11"
0?"
1@"
07
1<
0M
1N
0\
1]
0k
1l
0z
1{
0+"
1,"
b0 1
0:"
b1111111 0
1;"
0"
0,
1+
0F
1K
0U
1Z
0d
1i
0s
1x
0$"
1)"
03"
18"
0B"
1G"
0;
0:
09
0J
0I
0H
0G
0Y
0X
0W
0V
0h
0g
0f
0e
0w
0v
0u
0t
0("
0'"
0&"
0%"
07"
06"
05"
04"
0F"
0E"
0D"
0C"
0(
1)
b1 3
b1111 2
b1111 A
b1111 P
b1111 _
b1111 n
b1111 }
b1111 ."
b1111 ="
0#
b1 %
b1 '
b1 .
b11111111111111111111111111111111 $
b11111111111111111111111111111111 &
b11111111111111111111111111111111 -
#14000
1!
1#
#15000
1?"
1:"
10"
1+"
1!"
1z
1p
1k
1a
1\
1R
1M
0E
0T
0c
0r
0#"
02"
0A"
1C
0@
0O
0^
0m
0|
0-"
b0 /
0<"
b1111111 1
1>
0=
0D
0L
0S
0[
0b
0j
0q
0y
0""
0*"
01"
09"
0@"
17
0?
1F
0N
1U
0]
1d
0l
1s
0{
1$"
0,"
13"
b0 0
0;"
0<
0K
0Z
0i
0x
0)"
08"
1;
1:
19
1J
1I
1H
1G
1Y
1X
1W
1V
1h
1g
1f
1e
1w
1v
1u
1t
1("
1'"
1&"
1%"
17"
16"
15"
14"
1E"
1D"
1C"
b0 3
b0 2
b0 A
b0 P
b0 _
b0 n
b0 }
b0 ."
b1000 ="
b0 %
b0 '
b0 .
b10000000000000000000000000000000 $
b10000000000000000000000000000000 &
b10000000000000000000000000000000 -
#16000
1E
1T
1c
1r
1#"
12"
1A"
1*
1@
1O
1^
1m
1|
1-"
b1111111 /
1<"
1H"
1=
0C
1L
0R
1[
0a
1j
0p
1y
0!"
1*"
00"
19"
0?"
0+
0>
0M
0\
0k
0z
0+"
b0 1
0:"
0G"
07
0F
0U
0d
0s
0$"
03"
0;
0:
09
08
0J
0I
0H
0G
0Y
0X
0W
0V
0h
0g
0f
0e
0w
0v
0u
0t
0("
0'"
0&"
0%"
07"
06"
05"
04"
0E"
0D"
0C"
1!
1F"
1(
1)
b1111 3
b1111 B
b1111 Q
b1111 `
b1111 o
b1111 ~
b1111 /"
b111 >"
b0 ="
b1111111111111111111111111111111 %
b1111111111111111111111111111111 '
b1111111111111111111111111111111 .
b0 $
b0 &
b0 -
#17000
0E
0T
0c
0r
0#"
02"
0A"
0@
0O
0^
0m
0|
0-"
b0 /
0<"
1*
0=
1D
0L
1S
0[
1b
0j
1q
0y
1""
0*"
11"
09"
1@"
1H"
1?
1N
1]
1l
1{
1,"
b1111111 0
1;"
0+
1<
1K
1Z
1i
1x
1)"
18"
0G"
0!
0)
0F"
0(
b0 3
b0 B
b0 Q
b0 `
b0 o
b0 ~
b0 /"
b1000 >"
b1111 2
b1111 A
b1111 P
b1111 _
b1111 n
b1111 }
b1111 ."
b111 ="
b10000000000000000000000000000000 %
b10000000000000000000000000000000 '
b10000000000000000000000000000000 .
b1111111111111111111111111111111 $
b1111111111111111111111111111111 &
b1111111111111111111111111111111 -
#18000
1?"
1:"
10"
1+"
1!"
1z
1p
1k
1a
1\
1R
1M
0E
0T
0c
0r
0#"
02"
0A"
1C
0@
0O
0^
0m
0|
0-"
b0 /
0<"
b1111111 1
1>
0=
0D
0L
0S
0[
0b
0j
0q
0y
0""
0*"
01"
09"
0@"
17
0?
1F
0N
1U
0]
1d
0l
1s
0{
1$"
0,"
13"
b0 0
0;"
0<
0K
0Z
0i
0x
0)"
08"
1;
1:
19
18
1J
1I
1H
1G
1Y
1X
1W
1V
1h
1g
1f
1e
1w
1v
1u
1t
1("
1'"
1&"
1%"
17"
16"
15"
14"
1E"
1D"
1C"
1!
b0 2
b0 A
b0 P
b0 _
b0 n
b0 }
b0 ."
b0 ="
0#
b0 $
b0 &
b0 -
#19000
0!
0*
0H"
1+
1G"
1)
b0 >"
b1000 ="
b0 %
b0 '
b0 .
b10000000000000000000000000000000 $
b10000000000000000000000000000000 &
b10000000000000000000000000000000 -
#20000
1T
1r
1#"
12"
1O
1c
1m
1|
1-"
1L
1^
1j
1y
1*"
1[
0E
1D
0!"
0""
b111110 /
0@
1?
0R
0S
0p
0q
0z
0{
0?"
1@"
0=
0C
1<
0M
0N
0a
0b
0k
0l
0s
0x
00"
01"
0:"
1;"
0>
0F
0K
0\
0]
0d
0i
b0 1
0+"
b1000001 0
0,"
03"
18"
07
0U
0Z
0$"
0)"
08
0J
0Y
0W
0g
0w
0("
0E"
0:
0H
0V
0f
0v
0%"
05"
0C"
b1 3
b1000 B
b1110 Q
b101 `
b1001 o
b1000 ~
b100 >"
b100 2
b10 A
b101 P
b11 _
b101 n
b1 }
b10 ."
b1001 ="
b1000000100010010101111010000001 %
b1000000100010010101111010000001 '
b1000000100010010101111010000001 .
b10010010000101010011010100100100 $
b10010010000101010011010100100100 &
b10010010000101010011010100100100 -
#21000
0#"
0|
0y
1""
1{
0r
0A"
0[
1x
0m
b100110 /
0<"
1*
0j
1q
09"
1@"
1H"
1U
1l
b1011001 0
1;"
0+
1i
18"
0G"
09
1J
0I
1Y
1w
0'"
0&"
04"
1E"
0D"
0;
1:
18
1W
1V
0h
1g
1f
1("
06"
15"
1F"
1(
1)
1!
b11 3
b110 B
b110 Q
b0 o
b1111 ~
b1 /"
b11 >"
b1001 2
b0 A
b110 P
b1101 _
b100 n
b1000 }
b100 ."
b0 ="
1#
b110001111100000101011001100011 %
b110001111100000101011001100011 '
b110001111100000101011001100011 .
b100100001001101011000001001 $
b100100001001101011000001001 &
b100100001001101011000001001 -
#22000
1#"
1)
1|
1A"
1r
1!
1C
0D
0c
1y
0""
1<"
0@"
1m
1*
b1 1
1>
0?
b1111010 /
0^
0{
0;"
1b
1j
0q
1H"
17
0<
0x
13"
08"
1]
b100 0
0l
0+
0U
0B"
1Z
0i
0G"
1;
19
0J
1I
1H
0W
0g
0u
16"
14"
0E"
1D"
1C"
0f
1%"
b1101 3
b1000 B
b1001 Q
b1001 `
b1111 o
b1101 ~
b110 /"
b1100 >"
b1101 2
b1011 P
b111 _
b1001 n
b1011 }
b110 ."
b1000 ="
0#
b11000110110111111001100110001101 %
b11000110110111111001100110001101 '
b11000110110111111001100110001101 .
b10000110101110010111101100001101 $
b10000110101110010111101100001101 &
b10000110101110010111101100001101 -
#23000
0!
0)
0T
0O
0*
0L
1S
0r
19"
0H"
02"
1N
0m
1+
0c
0-"
1K
0j
1q
1G"
0^
0*"
11"
1l
1A"
0@"
0[
1b
1,"
0C
1D
1i
b1010000 /
1<"
0;"
1]
1)"
b0 1
0>
b101111 0
1?
08"
1Z
07
1<
03"
0:
09
08
1J
0G
0("
07"
05"
04"
1E"
0I
0H
0X
1f
0e
1u
0t
0%"
0D"
0C"
b10 3
b1 B
b10 Q
b101 `
b111 o
b11 ~
b1001 /"
b0 >"
b101 2
b110 A
b100 P
b1000 _
b10 n
b1100 }
b10 ."
b11 ="
1#
b1001001101110101001000010010 %
b1001001101110101001000010010 '
b1001001101110101001000010010 .
b110010110000101000010001100101 $
b110010110000101000010001100101 &
b110010110000101000010001100101 -
#24000
1T
1O
0r
02"
1E
1c
0m
0-"
1@
b1010111 /
1^
0j
1q
0*"
11"
1=
0D
0S
1[
0b
1!
1l
1,"
0+
0?
0N
b101000 0
0]
1*
1i
1)"
0G"
0<
1F
0K
0Z
1B"
0;
19
18
1G
0Y
1h
1e
1("
1'"
17"
06"
14"
1I
1H
1g
0f
1t
1%"
1D"
1C"
1)
b1101 3
b0 B
b1101 Q
b1100 `
b1101 ~
b110 /"
b1000 >"
b1 2
b0 A
b11 P
b1110 _
b11 n
b1111 }
b0 ."
b1000 ="
0#
b10000110110101111100110100001101 %
b10000110110101111100110100001101 '
b10000110110101111100110100001101 .
b10000000111100111110001100000001 $
b10000000111100111110001100000001 &
b10000000111100111110001100000001 -
